seatools/codegen/__init__.py
seatools/codegen/utils.py
seatools/codegen/ioc/__init__.py
seatools/codegen/ioc/app.py
seatools/codegen/ioc/cmd.py
seatools/codegen/ioc/common.py
seatools/codegen/ioc/django.py
seatools/codegen/ioc/fastapi.py
seatools/codegen/ioc/flask.py
seatools/codegen/ioc/grpc.py
seatools/codegen/ioc/main.py
seatools/codegen/ioc/scrapy.py
seatools/codegen/ioc/task.py
seatools_codegen-1.0.10.dist-info/LICENSE
seatools_codegen-1.0.10.dist-info/METADATA
seatools_codegen-1.0.10.dist-info/WHEEL
seatools_codegen-1.0.10.dist-info/entry_points.txt
seatools_codegen-1.0.10.dist-info/top_level.txt
seatools_codegen-1.0.10.dist-info/RECORD
