Metadata-Version: 2.1
Name: seatools-codegen
Version: 1.0.10
Summary: Cookiecutter-seatools-python 代码生成拓展包
Home-page: https://gitee.com/dragons96/cookiecutter-seatools-python-codegen
Author: dragons96
Author-email: 521274311@qq.com
License: MIT license
Keywords: seatools,codegen
Classifier: Development Status :: 2 - Pre-Alpha
Classifier: Intended Audience :: Developers
Classifier: License :: OSI Approved :: MIT License
Classifier: Natural Language :: English
Classifier: Programming Language :: Python :: 3.9
Requires-Python: >=3.9
License-File: LICENSE
Requires-Dist: loguru
Requires-Dist: click
Requires-Dist: toml
